MANIFEST.in
README.rst
setup.py
bin/zufaelliger-joke
docs/image01.jpg
scripts/zufaelliger-bash
zufaelliger/__init__.py
zufaelliger/command_line.py
zufaelliger.egg-info/PKG-INFO
zufaelliger.egg-info/SOURCES.txt
zufaelliger.egg-info/dependency_links.txt
zufaelliger.egg-info/entry_points.txt
zufaelliger.egg-info/not-zip-safe
zufaelliger.egg-info/requires.txt
zufaelliger.egg-info/top_level.txt