Metadata-Version: 1.1
Name: zufaelliger
Version: 0.2
Summary: Der komischsten Witz im Welt
Home-page: https://github.com/alexbmp/zufaelliger
Author: Fliegender Kirkus
Author-email: sm.alex.choi@gmail.com
License: MIT
Keywords: komisch Witz Comedy Zirkus
Platform: UNKNOWN
Classifier: Development Status :: 3 - Alpha
Classifier: License :: OSI Approved :: MIT License
Classifier: Programming Language :: Python :: 2.7
Classifier: Topic :: Text Processing :: Linguistic
